quantiq/__init__.py
quantiq/gates.py
quantiq/py.typed
quantiq/quantiq.py
quantiq/results.py
quantiq/simulator.py
quantiq/visualization.py
quantiq_dev-1.2.2.dist-info/licenses/LICENSE
quantiq_dev-1.2.2.dist-info/METADATA
quantiq_dev-1.2.2.dist-info/WHEEL
quantiq_dev-1.2.2.dist-info/top_level.txt
quantiq_dev-1.2.2.dist-info/RECORD
