Metadata-Version: 2.4
Name: quantiq-dev
Version: 1.2.2
Summary: Quantum computing with intelligence - learn, build, deploy
Author-email: Tony Rossi <anthony.rossi1983@gmail.com>
License: MIT
Project-URL: Homepage, https://quantiq.dev
Project-URL: Documentation, https://quantiq.dev/docs
Project-URL: Repository, https://github.com/tony-siqurity-ai/quantiq
Project-URL: Changelog, https://github.com/tony-siqurity-ai/quantiq/blob/main/CHANGELOG.md
Project-URL: Blog, https://quantiq.dev/blog
Keywords: quantum,quantum-computing,simulator,qubits,education,learning
Classifier: Development Status :: 4 - Beta
Classifier: Intended Audience :: Developers
Classifier: Intended Audience :: Education
Classifier: Intended Audience :: Science/Research
Classifier: License :: OSI Approved :: MIT License
Classifier: Programming Language :: Python :: 3
Classifier: Programming Language :: Python :: 3.11
Classifier: Programming Language :: Python :: 3.12
Classifier: Topic :: Scientific/Engineering :: Physics
Classifier: Topic :: Education
Requires-Python: >=3.11
License-File: LICENSE
Requires-Dist: numpy>=1.24.0
Provides-Extra: dev
Requires-Dist: pytest>=7.0; extra == "dev"
Requires-Dist: pytest-cov>=4.0; extra == "dev"
Requires-Dist: black>=23.0; extra == "dev"
Requires-Dist: flake8>=6.0; extra == "dev"
Requires-Dist: mypy>=1.0; extra == "dev"
Requires-Dist: isort>=5.0; extra == "dev"
Requires-Dist: pylint>=2.0; extra == "dev"
Dynamic: license-file
